<?xml version="1.0" encoding="utf-8" ?>
<dwsync>
<file name="Contacts.html" server="abdiconsultancy.com/abdiconsultancy.com/www/" local="129789837042577223" remote="129789850800000000" />
<file name="index.html" server="abdiconsultancy.com/abdiconsultancy.com/www/" local="129791583617732512" remote="129791583600000000" />
<file name="under-cons.html" server="abdiconsultancy.com/abdiconsultancy.com/www/" local="129789067210000000" remote="129789069600000000" />
<file name="about.html" server="abdiconsultancy.com/abdiconsultancy.com/www/" local="129789843440793180" remote="129789843600000000" />
<file name="News.html" server="abdiconsultancy.com/abdiconsultancy.com/www/" local="129785155012539476" remote="129785200200000000" />
<file name="contact.php" server="abdiconsultancy.com/abdiconsultancy.com/www/" local="129786248713084607" remote="129786255000000000" />
<file name="contact.asp" server="abdiconsultancy.com/abdiconsultancy.com/www/" local="129793054395648741" remote="129793065600000000" />
<file name="interested.asp" server="abdiconsultancy.com/abdiconsultancy.com/www/" local="129751561800000000" remote="129751561800000000" />
<file name="contact.html" server="abdiconsultancy.com/abdiconsultancy.com/www/" local="129783861600000000" remote="129783861600000000" />
<file name="Service.html" server="abdiconsultancy.com/abdiconsultancy.com/www/" local="129791525811046159" remote="129791525400000000" />
<file name="Services.html" server="abdiconsultancy.com/abdiconsultancy.com/www/" local="129783850020000000" remote="129788957400000000" />
<file name="education.html" server="abdiconsultancy.com/abdiconsultancy.com/www/" local="129792086236985289" remote="129792087000000000" />
<file name="web.html" server="abdiconsultancy.com/abdiconsultancy.com/www/" local="129751527000000000" remote="129751527000000000" />
<file name="itinfra.html" server="abdiconsultancy.com/abdiconsultancy.com/www/" local="129751528200000000" remote="129751528200000000" />
<file name="marketing.html" server="abdiconsultancy.com/abdiconsultancy.com/www/" local="129751528200000000" remote="129751528200000000" />
<file name="IT-Services.html" server="abdiconsultancy.com/abdiconsultancy.com/www/" local="129789117741748525" remote="129789118800000000" />
<file name="Management-Services.html" server="abdiconsultancy.com/abdiconsultancy.com/www/" local="129789117724637546" remote="129789118800000000" />
<file name="Products.html" server="abdiconsultancy.com/abdiconsultancy.com/www/" local="129789038040637846" remote="129789084600000000" />
<file name="education home.jpg" server="abdiconsultancy.com/abdiconsultancy.com/www/" local="129773125204105262" remote="129789834000000000" />
<file name="ralh.jpg" server="abdiconsultancy.com/abdiconsultancy.com/www/" local="129791528567003790" remote="129791530200000000" />
<file name="test.php" server="abdiconsultancy.com/abdiconsultancy.com/www/" local="129793040385677417" remote="129793043400000000" />
</dwsync>